README.rst
setup.cfg
setup.py
errbit_reporter/__init__.py
errbit_reporter/client.py
errbit_reporter/config.py
errbit_reporter/notice.py
errbit_reporter/version.py
errbit_reporter.egg-info/PKG-INFO
errbit_reporter.egg-info/SOURCES.txt
errbit_reporter.egg-info/dependency_links.txt
errbit_reporter.egg-info/requires.txt
errbit_reporter.egg-info/top_level.txt