Metadata-Version: 1.1
Name: errbit-reporter
Version: 0.0.3
Summary: Errbit Client
Home-page: https://github.com/dylanahsmith/errbit-reporter-python
Author: Dylan Thacker-Smith
Author-email: Dylan.Smith@shopify.com
License: MIT License
Platform: Any
Classifier: Development Status :: 3 - Alpha
Classifier: Intended Audience :: Developers
Classifier: License :: OSI Approved :: MIT License
Classifier: Operating System :: OS Independent
Classifier: Programming Language :: Python
Classifier: Programming Language :: Python :: 2
Classifier: Programming Language :: Python :: 2.7
Classifier: Programming Language :: Python :: 3
Classifier: Programming Language :: Python :: 3.4
Classifier: Topic :: Software Development :: Libraries :: Python Modules
